onec_codetemplate_parser/__init__.py
onec_codetemplate_parser/__main__.py
onec_codetemplate_parser/api.py
onec_codetemplate_parser/cli.py
onec_codetemplate_parser/core.py
onec_codetemplate_parser/parser.py
onec_codetemplate_parser/repository.py
onec_codetemplate_parser-1.0.2.dist-info/licenses/LICENSE
onec_codetemplate_parser-1.0.2.dist-info/METADATA
onec_codetemplate_parser-1.0.2.dist-info/WHEEL
onec_codetemplate_parser-1.0.2.dist-info/entry_points.txt
onec_codetemplate_parser-1.0.2.dist-info/top_level.txt
onec_codetemplate_parser-1.0.2.dist-info/RECORD
