Metadata-Version: 2.4
Name: onec_codetemplate_parser
Version: 1.0.2
Summary: Парсер шаблонов 1С
Author-email: Vladimir Nadulich <g240596448@gmail.com>
Maintainer-email: Vladimir Nadulich <g240596448@gmail.com>
License-Expression: MIT
Project-URL: Homepage, https://github.com/240596448/onec_codetemplate_parser
Project-URL: Documentation, https://github.com/240596448/onec_codetemplate_parser/blob/master/Readme.md
Project-URL: Repository, https://github.com/240596448/onec_codetemplate_parser.git
Project-URL: Bug Tracker, https://github.com/240596448/onec_codetemplate_parser/issues
Keywords: 1c,onec
Requires-Python: >=3.8
License-File: LICENSE
Requires-Dist: typer>=0.20.0
Provides-Extra: dev
Requires-Dist: pytest; extra == "dev"
Requires-Dist: pytest-cov; extra == "dev"
Requires-Dist: pytest-env; extra == "dev"
Dynamic: license-file
